invariantkernels/__init__.py
invariantkernels/invariant_kernel.py
invariantkernels/transformation_groups.py
invariantkernels-0.0.12.dist-info/LICENSE
invariantkernels-0.0.12.dist-info/METADATA
invariantkernels-0.0.12.dist-info/WHEEL
invariantkernels-0.0.12.dist-info/top_level.txt
invariantkernels-0.0.12.dist-info/RECORD
