Metadata-Version: 2.1
Name: invariantkernels
Version: 0.0.12
Summary: Transformation-invariant kernels in GPyTorch
Author-email: Theodore Brown <theo.brown.uk@gmail.com>
Project-URL: Homepage, https://github.com/theo-brown/invariantkernels
Classifier: License :: OSI Approved :: MIT License
Classifier: Programming Language :: Python :: 3
Classifier: Programming Language :: Python :: 3.8
Requires-Python: >=3.8
License-File: LICENSE
Requires-Dist: gpytorch
